flask_shell_bpython.py
flask_shell_bpython-0.0.1.dist-info/DESCRIPTION.rst
flask_shell_bpython-0.0.1.dist-info/METADATA
flask_shell_bpython-0.0.1.dist-info/RECORD
flask_shell_bpython-0.0.1.dist-info/WHEEL
flask_shell_bpython-0.0.1.dist-info/entry_points.txt
flask_shell_bpython-0.0.1.dist-info/metadata.json
flask_shell_bpython-0.0.1.dist-info/top_level.txt
